rapidpe_rift_pipe/__init__.py
rapidpe_rift_pipe/cli.py
rapidpe_rift_pipe/config.py
rapidpe_rift_pipe/create_submit_dag_one_event.py
rapidpe_rift_pipe/jacobians.py
rapidpe_rift_pipe/modules.py
rapidpe_rift_pipe/pastro.py
rapidpe_rift_pipe/postscript_utils.py
rapidpe_rift_pipe/profiling.py
rapidpe_rift_pipe/search_bias_bounds.py
rapidpe_rift_pipe/test_cli.py
rapidpe_rift_pipe/test_config.py
rapidpe_rift_pipe/test_modules.py
rapidpe_rift_pipe/utils.py
rapidpe_rift_pipe/config_files/__init__.py
rapidpe_rift_pipe/config_files/search_bias_bounds/__init__.py
rapidpe_rift_pipe/config_files/search_bias_bounds/default.json
rapidpe_rift_pipe/static/__init__.py
rapidpe_rift_pipe/static/stylesheet.css
rapidpe_rift_pipe-0.7.1.data/scripts/compute_posterior.py
rapidpe_rift_pipe-0.7.1.data/scripts/convert_result_to_txt.py
rapidpe_rift_pipe-0.7.1.data/scripts/cprofile_summary.py
rapidpe_rift_pipe-0.7.1.data/scripts/create_summarypage.py
rapidpe_rift_pipe-0.7.1.data/scripts/plot_skymap.py
rapidpe_rift_pipe-0.7.1.dist-info/licenses/COPYING
rapidpe_rift_pipe-0.7.1.dist-info/METADATA
rapidpe_rift_pipe-0.7.1.dist-info/WHEEL
rapidpe_rift_pipe-0.7.1.dist-info/entry_points.txt
rapidpe_rift_pipe-0.7.1.dist-info/top_level.txt
rapidpe_rift_pipe-0.7.1.dist-info/zip-safe
rapidpe_rift_pipe-0.7.1.dist-info/RECORD
