Metadata-Version: 2.4
Name: rapidpe_rift_pipe
Version: 0.7.1
Summary: Pipeline for running RapidPE and RIFT parameter estimation codes
License: GPL-2+
Keywords: parameter estimation,gravitational waves
Classifier: Development Status :: 3 - Alpha
Classifier: License :: OSI Approved :: GNU General Public License v2 or later (GPLv2+)
Classifier: Intended Audience :: Science/Research
Classifier: Natural Language :: English
Classifier: Programming Language :: Python :: 3
Classifier: Programming Language :: Python :: 3.9
Classifier: Programming Language :: Python :: 3.10
Classifier: Topic :: Scientific/Engineering
Classifier: Topic :: Scientific/Engineering :: Astronomy
Classifier: Topic :: Scientific/Engineering :: Physics
License-File: COPYING
Requires-Dist: numpy
Requires-Dist: matplotlib
Requires-Dist: h5py
Requires-Dist: tabulate
Requires-Dist: astropy
Requires-Dist: lalsuite!=7.15
Requires-Dist: gwpy>=3.0.4
Requires-Dist: rift<0.0.15.12,>=0.0.15.9
Requires-Dist: rapid_pe<0.2.0,>=0.1.1
Dynamic: license-file
